lib_not_dr/__init__.py
lib_not_dr/command/__init__.py
lib_not_dr/command/data.py
lib_not_dr/command/descriptor.py
lib_not_dr/command/exception.py
lib_not_dr/command/nodes.py
lib_not_dr/loggers/__init__.py
lib_not_dr/loggers/config.py
lib_not_dr/loggers/logger.py
lib_not_dr/loggers/outstream.py
lib_not_dr/loggers/structure.py
lib_not_dr/loggers/formatter/__init__.py
lib_not_dr/loggers/formatter/colors.py
lib_not_dr/nuitka/__init__.py
lib_not_dr/nuitka/compile.py
lib_not_dr/nuitka/reader/__init__.py
lib_not_dr/nuitka/reader/arg_parser.py
lib_not_dr/types/__init__.py
lib_not_dr/types/options.py
lib_not_dr/types/version.py
lndl_nuitka/__init__.py
lndl_nuitka/__main__.py
lib_not_dr-0.4.0.dist-info/LICENSE
lib_not_dr-0.4.0.dist-info/METADATA
lib_not_dr-0.4.0.dist-info/WHEEL
lib_not_dr-0.4.0.dist-info/entry_points.txt
lib_not_dr-0.4.0.dist-info/top_level.txt
lib_not_dr-0.4.0.dist-info/RECORD
