Metadata-Version: 2.1
Name: lib-not-dr
Version: 0.4.0
Summary: A python lib created from Difficult Rocket development
Author-email: shenjackyuanjie <3695888@qq.com>
License: MPL-2.0
Project-URL: Issues, https://github.com/shenjackyuanjie/lib-not-dr/issues
Project-URL: Homepage, https://github.com/shenjackyuanjie/lib-not-dr
Project-URL: Repository, https://github.com/shenjackyuanjie/lib-not-dr
Project-URL: Changelog, https://github.com/shenjackyuanjie/lib-not-dr/blob/main/docs/change_logs
Classifier: Intended Audience :: Developers
Classifier: Programming Language :: Python :: 3.8
Classifier: Programming Language :: Python :: 3.9
Classifier: Programming Language :: Python :: 3.10
Classifier: Programming Language :: Python :: 3.11
Classifier: Programming Language :: Python :: 3.12
Classifier: Programming Language :: Python :: Implementation :: CPython
Classifier: Programming Language :: Python :: Implementation :: PyPy
Classifier: Operating System :: OS Independent
Requires-Python: >=3.8
License-File: LICENSE
Provides-Extra: dev
Requires-Dist: twine ; extra == 'dev'
Provides-Extra: nuitka
Requires-Dist: tomli >=2.0.1 ; extra == 'nuitka'
Requires-Dist: nuitka ; extra == 'nuitka'
